MANIFEST.in
setup.py
docs/CONTRIBUTORS.txt
docs/HISTORY.txt
docs/LICENSE.ZPL
docs/LICENSE.txt
docs/README.txt
src/ztfy/__init__.py
src/ztfy.geoportal.egg-info/PKG-INFO
src/ztfy.geoportal.egg-info/SOURCES.txt
src/ztfy.geoportal.egg-info/dependency_links.txt
src/ztfy.geoportal.egg-info/entry_points.txt
src/ztfy.geoportal.egg-info/namespace_packages.txt
src/ztfy.geoportal.egg-info/not-zip-safe
src/ztfy.geoportal.egg-info/requires.txt
src/ztfy.geoportal.egg-info/top_level.txt
src/ztfy/geoportal/__init__.py
src/ztfy/geoportal/configure.zcml
src/ztfy/geoportal/interfaces.py
src/ztfy/geoportal/location.py
src/ztfy/geoportal/schema.py
src/ztfy/geoportal/utility.py
src/ztfy/geoportal/browser/__init__.py
src/ztfy/geoportal/browser/configure.zcml
src/ztfy/geoportal/browser/location.py
src/ztfy/geoportal/browser/test.py
src/ztfy/geoportal/browser/test.zcml
src/ztfy/geoportal/browser/resources/css/ztfy.geoportal.css
src/ztfy/geoportal/browser/resources/css/ztfy.geoportal.min.css
src/ztfy/geoportal/browser/resources/img/pin.png
src/ztfy/geoportal/browser/resources/js/ztfy.geoportal.js
src/ztfy/geoportal/browser/resources/js/ztfy.geoportal.min.js
src/ztfy/geoportal/browser/templates/location.pt
src/ztfy/geoportal/browser/widget/__init__.py
src/ztfy/geoportal/browser/widget/configure.zcml
src/ztfy/geoportal/browser/widget/location.py
src/ztfy/geoportal/browser/widget/templates/location_display.pt
src/ztfy/geoportal/browser/widget/templates/location_input.pt
src/ztfy/geoportal/doctests/README.txt
src/ztfy/geoportal/locales/ztfy.geoportal.pot
src/ztfy/geoportal/locales/en/LC_MESSAGES/ztfy.geoportal.mo
src/ztfy/geoportal/locales/en/LC_MESSAGES/ztfy.geoportal.po
src/ztfy/geoportal/locales/fr/LC_MESSAGES/ztfy.geoportal.mo
src/ztfy/geoportal/locales/fr/LC_MESSAGES/ztfy.geoportal.po
src/ztfy/geoportal/tests/__init__.py
src/ztfy/geoportal/tests/test_docs.py
src/ztfy/geoportal/tests/test_docstrings.py