Metadata-Version: 1.1
Name: ztfy.geoportal
Version: 0.2.4
Summary: ZTFY package for french IGN's GeoPortail access
Home-page: http://hg.ztfy.org/ztfy.geoportal
Author: Thierry Florac
Author-email: tflorac@ulthar.net
License: zpl
Keywords: ZTFY IGN GeoPortail
Platform: UNKNOWN
Classifier: License :: OSI Approved :: Zope Public License
Classifier: Development Status :: 4 - Beta
Classifier: Programming Language :: Python
Classifier: Framework :: Zope3
Classifier: Topic :: Software Development :: Libraries :: Python Modules
